supporting_information/TCR2HLA_allele_prevalence.py
supporting_information/TCR2HLA_validation_runs.py
tcr2hla-0.1.0.dist-info/licenses/LICENSE
tcr2hla-0.1.0.dist-info/licenses/LICENSE_MODELS
tcrtest/__init__.py
tcrtest/classify.py
tcrtest/collision.py
tcrtest/examples.py
tcrtest/find_across_cohort.py
tcrtest/hello.py
tcrtest/infer.py
tcrtest/nx.py
tcrtest/parse.py
tcrtest/paths.py
tcrtest/permutation.py
tcrtest/run.py
tcrtest/seqs_to_samples.py
tcrtest/similar.py
tcrtest/tabulate.py
tcrtest/testing.py
tcrtest/ui.py
tcrtest/models/XSTUDY_ALL_FEATURE_L1_v4e/XSTUDY_ALL_FEATURE_L1_v4e.calibrations.csv
tcrtest/models/XSTUDY_ALL_FEATURE_L1_v4e/XSTUDY_ALL_FEATURE_L1_v4e.columns.csv
tcrtest/models/XSTUDY_ALL_FEATURE_L1_v4e/XSTUDY_ALL_FEATURE_L1_v4e.intercepts.csv
tcrtest/models/XSTUDY_ALL_FEATURE_L1_v4e/XSTUDY_ALL_FEATURE_L1_v4e.query.csv
tcrtest/models/XSTUDY_ALL_FEATURE_L1_v4e/XSTUDY_ALL_FEATURE_L1_v4e.weights.npz
tcrtest/models/XSTUDY_ALL_FEATURE_L1_v4e/XSTUDY_ALL_FEATURE_L1_v4e_HS2.calibrations.csv
tests/__init__.py
tests/test_collision.py
tests/test_get_unique_collisions.py
tests/test_hello.py
tests/test_matrix_tab_with_missing_values.py
tests/test_permutation.py
tests/test_seqs_to_csr.py
tests/test_similar.py
tests/test_small_inference.py
tcr2hla-0.1.0.dist-info/METADATA
tcr2hla-0.1.0.dist-info/WHEEL
tcr2hla-0.1.0.dist-info/entry_points.txt
tcr2hla-0.1.0.dist-info/top_level.txt
tcr2hla-0.1.0.dist-info/RECORD
