Metadata-Version: 2.4
Name: TCR2HLA
Version: 0.1.0
Summary: Estimate HLA genotype probability from TCRb repertoire data
Author-email: "K.Mayer-Blackwell" <kmayerbl@fredhutch.org>
License-File: LICENSE
License-File: LICENSE_MODELS
Requires-Dist: numpy
Requires-Dist: pandas
Requires-Dist: scipy
Requires-Dist: psutil
Requires-Dist: tqdm
Requires-Dist: progress
Requires-Dist: parmap
Requires-Dist: scikit-learn
Provides-Extra: dev
Requires-Dist: pytest; extra == "dev"
Dynamic: license-file
